hmd_cli_librarian/__init__.py
hmd_cli_librarian/controller.py
hmd_cli_librarian/hmd_cli_librarian.py
hmd_cli_librarian/local_librarian_prj/meta-data/config_local.json
hmd_cli_librarian/local_librarian_prj/meta-data/manifest.json
hmd_cli_librarian/local_librarian_prj/src/python/setup.py
hmd_cli_librarian-0.1.19.dist-info/METADATA
hmd_cli_librarian-0.1.19.dist-info/WHEEL
hmd_cli_librarian-0.1.19.dist-info/top_level.txt
hmd_cli_librarian-0.1.19.dist-info/RECORD
